EnigmaDB/__init__.py
EnigmaDB/_database.py
EnigmaDB/_dataset.py
EnigmaDB/_queries.py
enigmadatabase-0.1.1.dist-info/licenses/LICENSE
enigmadatabase-0.1.1.dist-info/METADATA
enigmadatabase-0.1.1.dist-info/WHEEL
enigmadatabase-0.1.1.dist-info/top_level.txt
enigmadatabase-0.1.1.dist-info/RECORD
