Metadata-Version: 2.4
Name: enigmadatabase
Version: 0.1.1
Summary: NCBI DNA Database Builder and Dataset Loader for ML pipelines (Enigma2).
Author-email: shivendra <shivharsh44@gmail.com>
License-Expression: MIT
Project-URL: Source, https://github.com/delveopers/EnigmaDataset/
Project-URL: Documentation, https://devsorg.vercel.app/docs/EnigmaDataset/Database.md
Keywords: bioinformatics,ncbi,dna,fasta,entrez,dataset,machine-learning
Classifier: Development Status :: 4 - Beta
Classifier: Intended Audience :: Science/Research
Classifier: Topic :: Scientific/Engineering :: Bio-Informatics
Classifier: Programming Language :: Python :: 3
Classifier: Programming Language :: Python :: 3.8
Classifier: Programming Language :: Python :: 3.9
Classifier: Programming Language :: Python :: 3.10
Classifier: Programming Language :: Python :: 3.11
Requires-Python: >=3.9
License-File: LICENSE
Requires-Dist: biopython>=1.78
Requires-Dist: pandas>=1.0
Requires-Dist: pyarrow>=0.17
Requires-Dist: torch>=1.8
Requires-Dist: biosaic>=0.0.9
Requires-Dist: numpy>=1.19
Dynamic: license-file
